mypkg/__init__.py
mypkg/cleaner.py
mypkg/detector.py
mypkg/summarizer.py
wooseonghyun-0.1.1.dist-info/LICENSE
wooseonghyun-0.1.1.dist-info/METADATA
wooseonghyun-0.1.1.dist-info/WHEEL
wooseonghyun-0.1.1.dist-info/top_level.txt
wooseonghyun-0.1.1.dist-info/RECORD
