Metadata-Version: 2.1
Name: wooseonghyun
Version: 0.1.1
Summary: A simple text cleaner and keyword detector package.
Author: 우성현
Author-email: your@email.com
License: MIT
Classifier: Programming Language :: Python :: 3
Classifier: License :: OSI Approved :: MIT License
Classifier: Operating System :: OS Independent
Requires-Python: >=3.7
License-File: LICENSE
